odoo/addons/sale_stock_invoice_plan/README.rst
odoo/addons/sale_stock_invoice_plan/__init__.py
odoo/addons/sale_stock_invoice_plan/__manifest__.py
odoo/addons/sale_stock_invoice_plan/i18n/sale_stock_invoice_plan.pot
odoo/addons/sale_stock_invoice_plan/readme/CONTRIBUTORS.rst
odoo/addons/sale_stock_invoice_plan/readme/DESCRIPTION.rst
odoo/addons/sale_stock_invoice_plan/readme/HISTORY.rst
odoo/addons/sale_stock_invoice_plan/readme/INSTALL.rst
odoo/addons/sale_stock_invoice_plan/readme/USAGE.rst
odoo/addons/sale_stock_invoice_plan/security/ir.model.access.csv
odoo/addons/sale_stock_invoice_plan/static/description/icon.png
odoo/addons/sale_stock_invoice_plan/static/description/index.html
odoo/addons/sale_stock_invoice_plan/tests/__init__.py
odoo/addons/sale_stock_invoice_plan/tests/test_sale_invoice_plan.py
odoo_addon_sale_stock_invoice_plan-15.0.1.0.1.1.dist-info/METADATA
odoo_addon_sale_stock_invoice_plan-15.0.1.0.1.1.dist-info/WHEEL
odoo_addon_sale_stock_invoice_plan-15.0.1.0.1.1.dist-info/top_level.txt
odoo_addon_sale_stock_invoice_plan-15.0.1.0.1.1.dist-info/RECORD
