Metadata-Version: 2.1
Name: odoo-addon-sale-stock-invoice-plan
Version: 15.0.1.0.1.1
Summary: Add to sales order, ability to manage future invoice plan
Home-page: https://github.com/OCA/sale-workflow
Author: Ecosoft,Odoo Community Association (OCA)
Author-email: support@odoo-community.org
License: AGPL-3
Platform: UNKNOWN
Classifier: Programming Language :: Python
Classifier: Framework :: Odoo
Classifier: Framework :: Odoo :: 15.0
Classifier: License :: OSI Approved :: GNU Affero General Public License v3
Classifier: Development Status :: 3 - Alpha
Requires-Python: >=3.8
Requires-Dist: odoo-addon-sale-invoice-plan <15.1dev,>=15.0dev
Requires-Dist: odoo <15.1dev,>=15.0a
